djkit/__init__.py
djkit/dataclasses/misc.py
djkit/db/__init__.py
djkit/db/fields.py
djkit/models.py
djkit/private/__init__.py
djkit/private/errors.py
djkit/private/loggers.py
djkit/private/utils.py
djkit/rest_framework/pandas/__init__.py
djkit/rest_framework/polars/__init__.py
djkit/rest_framework/renderers.py
djkit/rest_framework/serializers.py
djkit/rest_framework/viewsets.py
djkit/utils.py
djkit-1.0.9.dist-info/LICENSE.txt
djkit-1.0.9.dist-info/METADATA
djkit-1.0.9.dist-info/WHEEL
djkit-1.0.9.dist-info/RECORD
