Metadata-Version: 2.1
Name: djkit
Version: 1.0.9
Summary: A library for handling common stuff in Django
License: MIT
Author: leondaz
Author-email: ahmeddark369@gmail.com
Requires-Python: >=3.9,<4.0
Classifier: License :: OSI Approved :: MIT License
Classifier: Programming Language :: Python :: 3
Classifier: Programming Language :: Python :: 3.9
Classifier: Programming Language :: Python :: 3.10
Classifier: Programming Language :: Python :: 3.11
Classifier: Programming Language :: Python :: 3.12
Provides-Extra: django
Provides-Extra: drf
Provides-Extra: pandas
Provides-Extra: polars
Requires-Dist: django (>=4.0,<5.0) ; extra == "django"
Requires-Dist: djangorestframework (>=3.10.0,<4.0.0) ; extra == "drf"
Requires-Dist: openpyxl (>=3.0.0,<4.0.0) ; extra == "pandas"
Requires-Dist: pandas (>=2.0.0,<3.0.0) ; extra == "pandas"
Requires-Dist: polars (>=0.20.2,<0.21.0) ; extra == "polars"
Requires-Dist: xlsx2csv (==0.8.2) ; extra == "polars"
Requires-Dist: xlsxwriter (>=3.1.0,<4.0.0) ; extra == "pandas"
